PyClockQ/__init__.py
pyclockq-1.0.0.dist-info/METADATA
pyclockq-1.0.0.dist-info/WHEEL
pyclockq-1.0.0.dist-info/top_level.txt
pyclockq-1.0.0.dist-info/RECORD
